tgcc/__init__.py
tgcc/cli.py
tgcc/md.py
tgcc-1.0.0.dist-info/METADATA
tgcc-1.0.0.dist-info/WHEEL
tgcc-1.0.0.dist-info/entry_points.txt
tgcc-1.0.0.dist-info/top_level.txt
tgcc-1.0.0.dist-info/RECORD
