Metadata-Version: 2.1
Name: tgcc
Version: 1.0.0
Summary: TechGeeks Compiler Collections
Home-page: https://github.com/TechGeeks-Dev/tgcc
Author: TechGeeks
Author-email: TGCompilers@tgeeks.cf
Maintainer: Rajdeep Malakar
Maintainer-email: Rajdeep@tgeeks.cf
License: UNKNOWN
Platform: UNKNOWN
Classifier: Programming Language :: Python :: 3
Classifier: License :: OSI Approved :: MIT License
Classifier: Operating System :: OS Independent
Requires-Python: >=3.6
Requires-Dist: markdown
